d8nmodels/__init__.py
d8nmodels/d8nmodels.py
d8nmodels/kafkaconfig.py
d8nmodels/result.py
d8nmodels/utils.py
d8nmodels-0.3.2.dist-info/METADATA
d8nmodels-0.3.2.dist-info/WHEEL
d8nmodels-0.3.2.dist-info/top_level.txt
d8nmodels-0.3.2.dist-info/RECORD
