Metadata-Version: 2.1
Name: d8nmodels
Version: 0.3.2
Summary: d8n API models python library
Author: Christo
Author-email: christochristov@duck.com
Classifier: Programming Language :: Python :: 3
Classifier: License :: OSI Approved :: MIT License
Classifier: Operating System :: OS Independent
Requires-Python: >=3.6
